pr0xyP3sr/__init__.py
pr0xyP3sr/pr0xyP3sr.py
pr0xyP3sr-0.1.dist-info/LICENSE
pr0xyP3sr-0.1.dist-info/METADATA
pr0xyP3sr-0.1.dist-info/WHEEL
pr0xyP3sr-0.1.dist-info/top_level.txt
pr0xyP3sr-0.1.dist-info/RECORD
