Metadata-Version: 2.1
Name: pr0xyP3sr
Version: 0.1
Summary: Load any recon data into burp in just Single click
Home-page: https://github.com/karthi-the-hacker/pr0xyP4rs3
Author: karthithehacker
Author-email: contact@karthithehacker.com
License: UNKNOWN
Platform: UNKNOWN
Classifier: Programming Language :: Python :: 3
Classifier: License :: OSI Approved :: MIT License
Classifier: Operating System :: OS Independent
License-File: LICENSE
